datastuff/__init__.py
datastuff-0.1.3.dist-info/LICENSE
datastuff-0.1.3.dist-info/WHEEL
datastuff-0.1.3.dist-info/METADATA
datastuff-0.1.3.dist-info/RECORD
